[
  {
    "gender": "female",
    "name": {
      "title": "Mrs",
      "first": "Marcia",
      "last": "Reid"
    },
    "phone": "(965)-955-0912",
    "id": {
      "name": "SSN",
      "value": "165-07-2640"
    },
    "picture": {
      "large": "https://randomuser.me/api/portraits/women/40.jpg",
      "medium": "https://randomuser.me/api/portraits/med/women/40.jpg",
      "thumbnail": "https://randomuser.me/api/portraits/thumb/women/40.jpg"
    }
  },
  {
    "gender": "female",
    "name": {
      "title": "Mrs",
      "first": "Debbie",
      "last": "Woods"
    },
    "phone": "(709)-536-2257",
    "id": {
      "name": "SSN",
      "value": "753-34-0955"
    },
    "picture": {
      "large": "https://randomuser.me/api/portraits/women/4.jpg",
      "medium": "https://randomuser.me/api/portraits/med/women/4.jpg",
      "thumbnail": "https://randomuser.me/api/portraits/thumb/women/4.jpg"
    }
  },
  {
    "gender": "male",
    "name": {
      "title": "Mr",
      "first": "Pedro",
      "last": "Steward"
    },
    "phone": "(801)-998-4492",
    "id": {
      "name": "SSN",
      "value": "151-80-0521"
    },
    "picture": {
      "large": "https://randomuser.me/api/portraits/men/69.jpg",
      "medium": "https://randomuser.me/api/portraits/med/men/69.jpg",
      "thumbnail": "https://randomuser.me/api/portraits/thumb/men/69.jpg"
    }
  },
  {
    "gender": "male",
    "name": {
      "title": "Mr",
      "first": "Marcus",
      "last": "Chavez"
    },
    "phone": "(661)-432-2551",
    "id": {
      "name": "SSN",
      "value": "587-04-5661"
    },
    "picture": {
      "large": "https://randomuser.me/api/portraits/men/84.jpg",
      "medium": "https://randomuser.me/api/portraits/med/men/84.jpg",
      "thumbnail": "https://randomuser.me/api/portraits/thumb/men/84.jpg"
    }
  },
  {
    "gender": "male",
    "name": {
      "title": "Mr",
      "first": "Miguel",
      "last": "Harvey"
    },
    "phone": "(825)-680-9553",
    "id": {
      "name": "SSN",
      "value": "267-44-9687"
    },
    "picture": {
      "large": "https://randomuser.me/api/portraits/men/86.jpg",
      "medium": "https://randomuser.me/api/portraits/med/men/86.jpg",
      "thumbnail": "https://randomuser.me/api/portraits/thumb/men/86.jpg"
    }
  },
  {
    "gender": "male",
    "name": {
      "title": "Mr",
      "first": "David",
      "last": "Knight"
    },
    "phone": "(574)-786-0558",
    "id": {
      "name": "SSN",
      "value": "495-87-3795"
    },
    "picture": {
      "large": "https://randomuser.me/api/portraits/men/5.jpg",
      "medium": "https://randomuser.me/api/portraits/med/men/5.jpg",
      "thumbnail": "https://randomuser.me/api/portraits/thumb/men/5.jpg"
    }
  },
  {
    "gender": "male",
    "name": {
      "title": "Mr",
      "first": "Austin",
      "last": "Matthews"
    },
    "phone": "(911)-719-0249",
    "id": {
      "name": "SSN",
      "value": "712-50-6278"
    },
    "picture": {
      "large": "https://randomuser.me/api/portraits/men/1.jpg",
      "medium": "https://randomuser.me/api/portraits/med/men/1.jpg",
      "thumbnail": "https://randomuser.me/api/portraits/thumb/men/1.jpg"
    }
  },
  {
    "gender": "male",
    "name": {
      "title": "Mr",
      "first": "Nathaniel",
      "last": "Bowman"
    },
    "phone": "(780)-826-5199",
    "id": {
      "name": "SSN",
      "value": "702-54-2894"
    },
    "picture": {
      "large": "https://randomuser.me/api/portraits/men/27.jpg",
      "medium": "https://randomuser.me/api/portraits/med/men/27.jpg",
      "thumbnail": "https://randomuser.me/api/portraits/thumb/men/27.jpg"
    }
  },
  {
    "gender": "female",
    "name": {
      "title": "Ms",
      "first": "Terry",
      "last": "Sims"
    },
    "phone": "(281)-112-8668",
    "id": {
      "name": "SSN",
      "value": "444-38-1559"
    },
    "picture": {
      "large": "https://randomuser.me/api/portraits/women/91.jpg",
      "medium": "https://randomuser.me/api/portraits/med/women/91.jpg",
      "thumbnail": "https://randomuser.me/api/portraits/thumb/women/91.jpg"
    }
  },
  {
    "gender": "male",
    "name": {
      "title": "Mr",
      "first": "Lonnie",
      "last": "Hicks"
    },
    "phone": "(958)-671-1440",
    "id": {
      "name": "SSN",
      "value": "602-12-5718"
    },
    "picture": {
      "large": "https://randomuser.me/api/portraits/men/10.jpg",
      "medium": "https://randomuser.me/api/portraits/med/men/10.jpg",
      "thumbnail": "https://randomuser.me/api/portraits/thumb/men/10.jpg"
    }
  },
  {
    "gender": "male",
    "name": {
      "title": "Mr",
      "first": "Lee",
      "last": "Hopkins"
    },
    "phone": "(380)-089-6908",
    "id": {
      "name": "SSN",
      "value": "322-67-5510"
    },
    "picture": {
      "large": "https://randomuser.me/api/portraits/men/23.jpg",
      "medium": "https://randomuser.me/api/portraits/med/men/23.jpg",
      "thumbnail": "https://randomuser.me/api/portraits/thumb/men/23.jpg"
    }
  },
  {
    "gender": "male",
    "name": {
      "title": "Mr",
      "first": "Ricardo",
      "last": "Mcdonalid"
    },
    "phone": "(710)-729-5844",
    "id": {
      "name": "SSN",
      "value": "281-32-9235"
    },
    "picture": {
      "large": "https://randomuser.me/api/portraits/men/17.jpg",
      "medium": "https://randomuser.me/api/portraits/med/men/17.jpg",
      "thumbnail": "https://randomuser.me/api/portraits/thumb/men/17.jpg"
    }
  },
  {
    "gender": "female",
    "name": {
      "title": "Ms",
      "first": "Wanda",
      "last": "Fuller"
    },
    "phone": "(950)-229-9525",
    "id": {
      "name": "SSN",
      "value": "828-14-5099"
    },
    "picture": {
      "large": "https://randomuser.me/api/portraits/women/85.jpg",
      "medium": "https://randomuser.me/api/portraits/med/women/85.jpg",
      "thumbnail": "https://randomuser.me/api/portraits/thumb/women/85.jpg"
    }
  },
  {
    "gender": "female",
    "name": {
      "title": "Mrs",
      "first": "Constance",
      "last": "Wallace"
    },
    "phone": "(652)-444-8726",
    "id": {
      "name": "SSN",
      "value": "779-48-4665"
    },
    "picture": {
      "large": "https://randomuser.me/api/portraits/women/60.jpg",
      "medium": "https://randomuser.me/api/portraits/med/women/60.jpg",
      "thumbnail": "https://randomuser.me/api/portraits/thumb/women/60.jpg"
    }
  },
  {
    "gender": "male",
    "name": {
      "title": "Mr",
      "first": "Tom",
      "last": "Rodriquez"
    },
    "phone": "(511)-890-0574",
    "id": {
      "name": "SSN",
      "value": "968-78-7323"
    },
    "picture": {
      "large": "https://randomuser.me/api/portraits/men/32.jpg",
      "medium": "https://randomuser.me/api/portraits/med/men/32.jpg",
      "thumbnail": "https://randomuser.me/api/portraits/thumb/men/32.jpg"
    }
  },
  {
    "gender": "male",
    "name": {
      "title": "Mr",
      "first": "Tyler",
      "last": "Herrera"
    },
    "phone": "(022)-217-5330",
    "id": {
      "name": "SSN",
      "value": "363-38-8279"
    },
    "picture": {
      "large": "https://randomuser.me/api/portraits/men/70.jpg",
      "medium": "https://randomuser.me/api/portraits/med/men/70.jpg",
      "thumbnail": "https://randomuser.me/api/portraits/thumb/men/70.jpg"
    }
  },
  {
    "gender": "male",
    "name": {
      "title": "Mr",
      "first": "Roland",
      "last": "Scott"
    },
    "phone": "(489)-548-8240",
    "id": {
      "name": "SSN",
      "value": "291-80-6720"
    },
    "picture": {
      "large": "https://randomuser.me/api/portraits/men/76.jpg",
      "medium": "https://randomuser.me/api/portraits/med/men/76.jpg",
      "thumbnail": "https://randomuser.me/api/portraits/thumb/men/76.jpg"
    }
  },
  {
    "gender": "male",
    "name": {
      "title": "Mr",
      "first": "Alfred",
      "last": "Barrett"
    },
    "phone": "(811)-437-3155",
    "id": {
      "name": "SSN",
      "value": "854-48-8326"
    },
    "picture": {
      "large": "https://randomuser.me/api/portraits/men/19.jpg",
      "medium": "https://randomuser.me/api/portraits/med/men/19.jpg",
      "thumbnail": "https://randomuser.me/api/portraits/thumb/men/19.jpg"
    }
  },
  {
    "gender": "male",
    "name": {
      "title": "Mr",
      "first": "Ryan",
      "last": "Fernandez"
    },
    "phone": "(292)-477-0062",
    "id": {
      "name": "SSN",
      "value": "665-44-1956"
    },
    "picture": {
      "large": "https://randomuser.me/api/portraits/men/80.jpg",
      "medium": "https://randomuser.me/api/portraits/med/men/80.jpg",
      "thumbnail": "https://randomuser.me/api/portraits/thumb/men/80.jpg"
    }
  },
  {
    "gender": "female",
    "name": {
      "title": "Ms",
      "first": "Kim",
      "last": "Sutton"
    },
    "phone": "(715)-245-4628",
    "id": {
      "name": "SSN",
      "value": "186-49-8668"
    },
    "picture": {
      "large": "https://randomuser.me/api/portraits/women/43.jpg",
      "medium": "https://randomuser.me/api/portraits/med/women/43.jpg",
      "thumbnail": "https://randomuser.me/api/portraits/thumb/women/43.jpg"
    }
  }
]
